cinx/__init__.py
cinx/interpolation.py
cinx/test_interpolation.py
cinx-0.0.1.dist-info/METADATA
cinx-0.0.1.dist-info/WHEEL
cinx-0.0.1.dist-info/top_level.txt
cinx-0.0.1.dist-info/RECORD
