Metadata-Version: 2.4
Name: cinx
Version: 0.0.1
Summary: Very minimal and straightforward cubic interpolation on splines in JAX. Pure differentiable JAX.
Author-email: Albert Alonso <aaf@di.ku.dk>, Frans Zdyb <frzd@di.ku.dk>
Project-URL: Homepage, https://github.com/alonfnt/cinx
Project-URL: Documentation, https://github.com/alonfnt/cinx
Project-URL: Source, https://github.com/alonfnt/cinx
Project-URL: Bug Tracker, https://github.com/alonfnt/cinx/issues
Keywords: jax,interpolation,cubic-spline,automatic-differentiation,scientific-computing
Classifier: Programming Language :: Python :: 3
Classifier: License :: OSI Approved :: MIT License
Classifier: Intended Audience :: Science/Research
Classifier: Topic :: Scientific/Engineering
Requires-Dist: jax
Provides-Extra: dev
Requires-Dist: pytest; extra == "dev"
Requires-Dist: black; extra == "dev"
